HISTORY.rst
LICENSE
MANIFEST.in
README.rst
setup.py
tanto
etc/.placeholder
etc/cron.d/tanto
etc/tanto/logging.ini
etc/tanto/inputs/nagios_plugins.cfg
etc/tanto/outputs/email.cfg
etc/tanto/outputs/nsca.cfg
etc/tanto/outputs/ws_shinken.cfg
monitoring_agent/__init__.py
monitoring_agent/configurator.py
monitoring_agent/inputs/__init__.py
monitoring_agent/inputs/nagios_plugins.py
monitoring_agent/inputs/configspecs/nagios_plugins.cfg
monitoring_agent/outputs/__init__.py
monitoring_agent/outputs/email.py
monitoring_agent/outputs/nsca.py
monitoring_agent/outputs/ws_shinken.py
monitoring_agent/outputs/configspecs/email.cfg
monitoring_agent/outputs/configspecs/nsca.cfg
monitoring_agent/outputs/configspecs/ws_shinken.cfg
tanto.egg-info/PKG-INFO
tanto.egg-info/SOURCES.txt
tanto.egg-info/dependency_links.txt
tanto.egg-info/not-zip-safe
tanto.egg-info/requires.txt
tanto.egg-info/top_level.txt