Metadata-Version: 1.1
Name: tanto
Version: 1.1
Summary: Takes monitoring data from Nagios-plugins to push with NSCA (Nagios or Icinga) or WS-Shinken.
Home-page: https://github.com/Eyepea/tanto
Author: Ludovic Gasc
Author-email: ludovic.gasc@eyepea.eu
License: GNU Affero General Public License v3
Platform: UNIX
Classifier: Development Status :: 5 - Production/Stable
Classifier: Environment :: Console
Classifier: Environment :: No Input/Output (Daemon)
Classifier: Intended Audience :: System Administrators
Classifier: License :: OSI Approved :: GNU Affero General Public License v3
Classifier: Natural Language :: English
Classifier: Operating System :: POSIX
Classifier: Programming Language :: Python
Classifier: Programming Language :: Python :: 2.6
Classifier: Programming Language :: Python :: 2.7
Classifier: Programming Language :: Python :: Implementation :: CPython
Classifier: Topic :: System :: Monitoring
Classifier: Topic :: System :: Networking :: Monitoring
